my_breakout_package/__init__.py
my_breakout_package/breakout.py
my_breakout_package-0.1.dist-info/METADATA
my_breakout_package-0.1.dist-info/WHEEL
my_breakout_package-0.1.dist-info/top_level.txt
my_breakout_package-0.1.dist-info/RECORD
